mapilio_kit/__init__.py
mapilio_kit/__main__.py
mapilio_kit/base/__init__.py
mapilio_kit/base/authenticate.py
mapilio_kit/base/decompose.py
mapilio_kit/base/gopro_360max.py
mapilio_kit/base/image_and_csv_upload.py
mapilio_kit/base/loader.py
mapilio_kit/base/process_csv.py
mapilio_kit/base/run.py
mapilio_kit/base/sampler.py
mapilio_kit/base/video_upload.py
mapilio_kit/base/zip.py
mapilio_kit/components/__init__.py
mapilio_kit/components/logger.py
mapilio_kit/components/version.py
mapilio_kit/components/auth/__init__.py
mapilio_kit/components/auth/auth_config.py
mapilio_kit/components/auth/login.py
mapilio_kit/components/blending/__init__.py
mapilio_kit/components/blending/basics_blender.py
mapilio_kit/components/blending/struct_blender.py
mapilio_kit/components/blending/video_blender.py
mapilio_kit/components/geotagging/__init__.py
mapilio_kit/components/geotagging/geotag_property_handler.py
mapilio_kit/components/geotagging/geotagger.py
mapilio_kit/components/geotagging/gopro_location_filter.py
mapilio_kit/components/geotagging/gopro_parser.py
mapilio_kit/components/geotagging/gps_from_gopro360.py
mapilio_kit/components/geotagging/gps_parser.py
mapilio_kit/components/geotagging/gpx_from_exif.py
mapilio_kit/components/geotagging/gpx_from_gopro.py
mapilio_kit/components/ipc/__init__.py
mapilio_kit/components/ipc/interprocess_communication.py
mapilio_kit/components/logs/__init__.py
mapilio_kit/components/logs/image_log.py
mapilio_kit/components/metadata/__init__.py
mapilio_kit/components/metadata/exif_metadata_reader.py
mapilio_kit/components/metadata/exif_metadata_writer.py
mapilio_kit/components/metadata/metadata_property_handler.py
mapilio_kit/components/processing/__init__.py
mapilio_kit/components/processing/cam_data_processor.py
mapilio_kit/components/processing/export.py
mapilio_kit/components/processing/ffmpeg.py
mapilio_kit/components/processing/gpmf.py
mapilio_kit/components/processing/process_csv_to_description.py
mapilio_kit-3.0.5.dist-info/LICENSE
mapilio_kit-3.0.5.dist-info/METADATA
mapilio_kit-3.0.5.dist-info/WHEEL
mapilio_kit-3.0.5.dist-info/entry_points.txt
mapilio_kit-3.0.5.dist-info/top_level.txt
mapilio_kit-3.0.5.dist-info/RECORD
